mikas_attribute_checker/AttributeChecker.py
mikas_attribute_checker/__init__.py
mikas_attribute_checker-0.0.2.dist-info/LICENSE
mikas_attribute_checker-0.0.2.dist-info/METADATA
mikas_attribute_checker-0.0.2.dist-info/WHEEL
mikas_attribute_checker-0.0.2.dist-info/top_level.txt
mikas_attribute_checker-0.0.2.dist-info/RECORD
