Metadata-Version: 2.1
Name: mikas_attribute_checker
Version: 0.0.2
Summary: Generic attribute checker classes
Author: Mika Silander
Author-email: mika.silander@iki.fi
License: UNKNOWN
Platform: UNKNOWN
Classifier: Development Status :: 1 - Planning
Classifier: Programming Language :: Python :: 3 :: Only
Classifier: License :: OSI Approved :: MIT License
Classifier: Intended Audience :: Developers
Classifier: Operating System :: POSIX :: Linux
Classifier: Topic :: Software Development :: Libraries :: Python Modules
Requires-Python: >=3.6
License-File: LICENSE
